{
  "project_info": {
    "project_number": "1032358095771",
    "project_id": "smartlock-c3e93",
    "storage_bucket": "smartlock-c3e93.appspot.com"
  },
  "client": [
    {
      "client_info": {
        "mobilesdk_app_id": "1:1032358095771:android:da931c4c3b0f860fa6cf3e",
        "android_client_info": {
          "package_name": "com.example.smart_lock"
        }
      },
      "oauth_client": [
        {
          "client_id": "1032358095771-h7pf61dl0mdg88jtjrf3t5nsph5cqh51.apps.googleusercontent.com",
          "client_type": 3
        }
      ],
      "api_key": [
        {
          "current_key": "AIzaSyDmR8jDH0KQqoxZpNPmvZZaMMHAqckarEo"
        }
      ],
      "services": {
        "appinvite_service": {
          "other_platform_oauth_client": [
            {
              "client_id": "1032358095771-h7pf61dl0mdg88jtjrf3t5nsph5cqh51.apps.googleusercontent.com",
              "client_type": 3
            }
          ]
        }
      }
    }
  ],
  "configuration_version": "1"
}